{
  "db_name": "SQLite",
  "query": "SELECT word, offset FROM dictionary_index_entry WHERE dict_id = ? LIMIT ?",
  "describe": {
    "columns": [
      {
        "name": "word",
        "ordinal": 0,
        "type_info": "Text"
      },
      {
        "name": "offset",
        "ordinal": 1,
        "type_info": "Integer"
      }
    ],
    "parameters": {
      "Right": 2
    },
    "nullable": [
      false,
      false
    ]
  },
  "hash": "9df58f98329eddad68ccb464dcec346042e7573735b717dbfec78d53551ee8c1"
}
